sprockets.logging-1.3.2-py3.4-nspkg.pth
sprockets/logging/__init__.py
sprockets.logging-1.3.2.dist-info/zip-safe
sprockets.logging-1.3.2.dist-info/top_level.txt
sprockets.logging-1.3.2.dist-info/namespace_packages.txt
sprockets.logging-1.3.2.dist-info/METADATA
sprockets.logging-1.3.2.dist-info/DESCRIPTION.rst
sprockets.logging-1.3.2.dist-info/metadata.json
sprockets.logging-1.3.2.dist-info/WHEEL
sprockets.logging-1.3.2.dist-info/RECORD
