Metadata-Version: 2.0
Name: sprockets.logging
Version: 1.3.2
Summary: Making logs nicer since 2015!
Home-page: https://github.com/sprockets/sprockets.logging.git
Author: Dave Shawley
Author-email: daves@aweber.com
License: BSD
Platform: UNKNOWN
Classifier: Development Status :: 5 - Production/Stable
Classifier: Intended Audience :: Developers
Classifier: License :: OSI Approved :: BSD License
Classifier: Natural Language :: English
Classifier: Operating System :: OS Independent
Classifier: Programming Language :: Python :: 2
Classifier: Programming Language :: Python :: 2.7
Classifier: Programming Language :: Python :: 3
Classifier: Programming Language :: Python :: 3.4
Classifier: Programming Language :: Python :: Implementation :: CPython
Classifier: Programming Language :: Python :: Implementation :: PyPy
Classifier: Topic :: Software Development :: Libraries
Classifier: Topic :: Software Development :: Libraries :: Python Modules
Provides-Extra: tornado
Requires-Dist: tornado (>3,<5); extra == 'tornado'
